detra/__init__.py
detra/client.py
detra/actions/__init__.py
detra/actions/alerts.py
detra/actions/cases.py
detra/actions/incidents.py
detra/actions/notifications.py
detra/agents/__init__.py
detra/agents/monitor.py
detra/agents/tools.py
detra/agents/workflow.py
detra/config/__init__.py
detra/config/defaults.py
detra/config/loader.py
detra/config/schema.py
detra/dashboard/__init__.py
detra/dashboard/builder.py
detra/dashboard/comprehensive_template.py
detra/decorators/__init__.py
detra/decorators/trace.py
detra/detection/__init__.py
detra/detection/monitors.py
detra/detection/rules.py
detra/detection/templates.py
detra/errors/__init__.py
detra/errors/context.py
detra/errors/grouper.py
detra/errors/tracker.py
detra/evaluation/__init__.py
detra/evaluation/classifiers.py
detra/evaluation/engine.py
detra/evaluation/gemini_judge.py
detra/evaluation/prompts.py
detra/evaluation/rules.py
detra/optimization/__init__.py
detra/optimization/dspy_optimizer.py
detra/optimization/root_cause.py
detra/security/__init__.py
detra/security/scanners.py
detra/security/signals.py
detra/telemetry/__init__.py
detra/telemetry/datadog_client.py
detra/telemetry/events.py
detra/telemetry/llmobs_bridge.py
detra/telemetry/logs.py
detra/telemetry/metrics.py
detra/telemetry/traces.py
detra/utils/__init__.py
detra/utils/retry.py
detra/utils/serialization.py
detra-0.1.0.dist-info/METADATA
detra-0.1.0.dist-info/WHEEL
detra-0.1.0.dist-info/licenses/LICENSE
detra-0.1.0.dist-info/RECORD
