Metadata-Version: 2.4
Name: detra
Version: 0.1.0
Summary: End-to-end LLM observability for vertical AI applications with Datadog
Project-URL: Homepage, https://github.com/adc77/detra
Project-URL: Repository, https://github.com/adc77/detra
Project-URL: Documentation, https://github.com/adc77/detra#readme
Project-URL: Issues, https://github.com/adc77/detra/issues
Author: detra Contributors
License: MIT
License-File: LICENSE
Keywords: ai,datadog,evaluation,llm,ml,monitoring,observability,security,tracing,vertical-ai
Classifier: Development Status :: 4 - Beta
Classifier: Intended Audience :: Developers
Classifier: Intended Audience :: Science/Research
Classifier: License :: OSI Approved :: MIT License
Classifier: Operating System :: OS Independent
Classifier: Programming Language :: Python :: 3
Classifier: Programming Language :: Python :: 3.10
Classifier: Programming Language :: Python :: 3.11
Classifier: Programming Language :: Python :: 3.12
Classifier: Programming Language :: Python :: 3.13
Classifier: Topic :: Scientific/Engineering :: Artificial Intelligence
Classifier: Topic :: Software Development :: Libraries :: Python Modules
Classifier: Topic :: System :: Logging
Classifier: Topic :: System :: Monitoring
Requires-Python: >=3.11
Requires-Dist: certifi>=2024.2.2
Requires-Dist: datadog-api-client>=2.20.0
Requires-Dist: datadog>=0.49.0
Requires-Dist: ddtrace>=2.10.0
Requires-Dist: google-cloud-aiplatform>=1.40.0
Requires-Dist: google-genai>=0.2.0
Requires-Dist: httpx>=0.26.0
Requires-Dist: pydantic-settings>=2.1.0
Requires-Dist: pydantic>=2.5.0
Requires-Dist: python-dotenv>=1.0.0
Requires-Dist: pyyaml>=6.0.1
Requires-Dist: structlog>=24.1.0
Requires-Dist: tenacity>=8.2.0
Requires-Dist: tiktoken>=0.5.0
Provides-Extra: all
Requires-Dist: dspy-ai>=2.4.0; extra == 'all'
Requires-Dist: mypy>=1.8.0; extra == 'all'
Requires-Dist: pytest-asyncio>=0.23.0; extra == 'all'
Requires-Dist: pytest-cov>=4.1.0; extra == 'all'
Requires-Dist: pytest>=8.0.0; extra == 'all'
Requires-Dist: ruff>=0.2.0; extra == 'all'
Provides-Extra: dev
Requires-Dist: mypy>=1.8.0; extra == 'dev'
Requires-Dist: pytest-asyncio>=0.23.0; extra == 'dev'
Requires-Dist: pytest-cov>=4.1.0; extra == 'dev'
Requires-Dist: pytest>=8.0.0; extra == 'dev'
Requires-Dist: ruff>=0.2.0; extra == 'dev'
Provides-Extra: optimization
Requires-Dist: dspy-ai>=2.4.0; extra == 'optimization'
Provides-Extra: server
Requires-Dist: fastapi>=0.104.0; extra == 'server'
Requires-Dist: uvicorn[standard]>=0.24.0; extra == 'server'
